{
	"disclaimer": "This data is collected from various providers and provided free of charge for informational purposes only, with no guarantee whatsoever of accuracy, validity, availability or fitness for any purpose; use at your own risk. Other than that - have fun, and please share/watch/fork if you think data like this should be free!",
	"license": "Data collected from various providers with public-facing APIs; copyright may apply; not for resale; no warranties given.",
	"timestamp": 1331541264,
	"base": "USD",
	"rates": {
		"AED": 3.6731,
		"AFN": 48.279999,
		"ALL": 106.699997,
		"AMD": 389.790009,
		"ANG": 1.79,
		"AOA": 94.949997,
		"ARS": 4.338,
		"AUD": 0.950029,
		"AWG": 1.7899,
		"AZN": 0.7863,
		"BAM": 1.49515,
		"BBD": 2,
		"BDT": 81.760002,
		"BGN": 1.4945,
		"BHD": 0.37703,
		"BIF": 1308,
		"BMD": 1,
		"BND": 1.26055,
		"BOB": 6.91,
		"BRL": 1.7918,
		"BSD": 1,
		"BTN": 49.962502,
		"BWP": 7.2307,
		"BYR": 8200,
		"BZD": 1.9135,
		"CAD": 0.99123,
		"CDF": 923.865112,
		"CHF": 0.91992,
		"CLF": 0.02153,
		"CLP": 483.850006,
		"CNY": 6.3258,
		"COP": 1762.699951,
		"CRC": 510.200012,
		"CUP": 1,
		"CVE": 83.650002,
		"CZK": 18.810301,
		"DJF": 179.550003,
		"DKK": 5.6741,
		"DOP": 38.849998,
		"DZD": 74.690002,
		"EGP": 6.0325,
		"ETB": 17.43845,
		"EUR": 0.763024,
		"FJD": 1.7671,
		"FKP": 0.638,
		"GBP": 0.637879,
		"GEL": 1.65085,
		"GHS": 1.7175,
		"GIP": 0.638,
		"GMD": 30.51,
		"GNF": 7100,
		"GTQ": 7.7395,
		"GYD": 203.199997,
		"HKD": 7.75883,
		"HNL": 19.055,
		"HRK": 5.7605,
		"HTG": 41,
		"HUF": 223.684998,
		"IDR": 9135,
		"IEP": 0.600727,
		"ILS": 3.79775,
		"INR": 49.985001,
		"IQD": 1165.5,
		"IRR": 12260,
		"ISK": 125.239998,
		"JMD": 86.720001,
		"JOD": 0.71,
		"JPY": 82.153,
		"KES": 82.599998,
		"KGS": 46.556,
		"KHR": 4010,
		"KMF": 375.261444,
		"KPW": 900,
		"KRW": 1124.469971,
		"KWD": 0.2787,
		"KZT": 147.925003,
		"LAK": 7952.5,
		"LBP": 1505.5,
		"LKR": 121.849998,
		"LRD": 73.25,
		"LSL": 7.595,
		"LTL": 2.63485,
		"LVL": 0.5315,
		"LYD": 1.2596,
		"MAD": 8.4997,
		"MDL": 11.812,
		"MGA": 2160,
		"MKD": 46.880001,
		"MMK": 6.51,
		"MNT": 1322.5,
		"MOP": 7.99075,
		"MRO": 292.5,
		"MUR": 29.299999,
		"MVR": 15.37,
		"MWK": 165.466599,
		"MXN": 12.67885,
		"MYR": 3.0305,
		"MZN": 27.1,
		"NAD": 7.535,
		"NGN": 157.570007,
		"NIO": 23.195,
		"NOK": 5.7099,
		"NPR": 79.940002,
		"NZD": 1.223264,
		"OMR": 0.38505,
		"PAB": 1,
		"PEN": 2.67,
		"PGK": 2.0555,
		"PHP": 42.700001,
		"PKR": 90.595001,
		"PLN": 3.13115,
		"PYG": 4245,
		"QAR": 3.6417,
		"RON": 3.3247,
		"RSD": 84.435501,
		"RUB": 29.5683,
		"RWF": 606.717529,
		"SAR": 3.75035,
		"SBD": 7.075973,
		"SCR": 14.0447,
		"SDG": 2.6769,
		"SEK": 6.80835,
		"SGD": 1.2612,
		"SHP": 0.638,
		"SLL": 4375,
		"SOS": 1627,
		"SRD": 3.275,
		"STD": 18602.5,
		"SVC": 8.7475,
		"SYP": 57.450001,
		"SZL": 7.599,
		"THB": 30.65,
		"TJS": 4.7592,
		"TMT": 2.845,
		"TND": 1.5197,
		"TOP": 1.679379,
		"TRY": 1.7953,
		"TTD": 6.407,
		"TWD": 29.521999,
		"TZS": 1594.5,
		"UAH": 8.027,
		"UGX": 2450,
		"USD": 1,
		"UYU": 19.549999,
		"UZS": 1827.890015,
		"VEF": 4.2927,
		"VND": 20815,
		"VUV": 89.099998,
		"WST": 2.234916,
		"XAF": 500.348602,
		"XCD": 2.7,
		"XDR": 0.648479,
		"XOF": 500.549988,
		"XPF": 91.300003,
		"YER": 216.005005,
		"ZAR": 7.59235,
		"ZMK": 5266,
		"ZWD": 378.700012,
		"ZWL": 322.355011
	}
}
