{
	"disclaimer": "This data is collected from various providers and provided free of charge for informational purposes only, with no guarantee whatsoever of accuracy, validity, availability, or fitness for any purpose; use at your own risk. Other than that, have fun! More info: http://openexchangerates.org/terms/",
	"license": "Data collected from various providers with public-facing APIs; copyright may apply; not for resale; no warranties given. Full license info: http://openexchangerates.org/license/",
	"timestamp": 1337880516,
	"base": "USD",
	"rates": {
		"AED": 3.6731,
		"AFN": 48.48,
		"ALL": 110.959999,
		"AMD": 402.670013,
		"ANG": 1.79,
		"AOA": 95.341499,
		"ARS": 4.468,
		"AUD": 1.027364,
		"AWG": 1.7899,
		"AZN": 0.786,
		"BAM": 1.56175,
		"BBD": 2,
		"BDT": 81.879997,
		"BGN": 1.55,
		"BHD": 0.3769,
		"BIF": 1400,
		"BMD": 1,
		"BND": 1.27765,
		"BOB": 6.91,
		"BRL": 2.0387,
		"BSD": 1,
		"BTN": 55.779999,
		"BWP": 7.722,
		"BYR": 8260,
		"BZD": 1.9135,
		"CAD": 1.02835,
		"CDF": 924.49939,
		"CHF": 0.95781,
		"CLF": 0.02246,
		"CLP": 508.200012,
		"CNH": 6.2995,
		"CNY": 6.3476,
		"COP": 1840.5,
		"CRC": 505,
		"CUP": 1,
		"CVE": 87.75,
		"CZK": 20.282,
		"DJF": 180.979996,
		"DKK": 5.92215,
		"DOP": 39.049999,
		"DZD": 75.697998,
		"EGP": 6.0395,
		"ETB": 17.6681,
		"EUR": 0.796857,
		"FJD": 1.8653,
		"FKP": 0.6378,
		"GBP": 0.638064,
		"GEL": 1.6268,
		"GHS": 1.892,
		"GIP": 0.63785,
		"GMD": 30.690001,
		"GNF": 7025,
		"GTQ": 7.785,
		"GYD": 203.449997,
		"HKD": 7.76382,
		"HNL": 19.055,
		"HRK": 6.0346,
		"HTG": 41.970001,
		"HUF": 239.160004,
		"IDR": 9265,
		"IEP": 0.627865,
		"ILS": 3.85315,
		"INR": 55.825001,
		"IQD": 1164.25,
		"IRR": 12275,
		"ISK": 129.020004,
		"JMD": 87.25,
		"JOD": 0.709,
		"JPY": 79.556999,
		"KES": 85.199997,
		"KGS": 47.2616,
		"KHR": 4030,
		"KMF": 392.20929,
		"KPW": 900,
		"KRW": 1179.900024,
		"KWD": 0.28005,
		"KZT": 147.720001,
		"LAK": 8000.5,
		"LBP": 1503,
		"LKR": 130.5,
		"LRD": 74.300003,
		"LSL": 8.37,
		"LTL": 2.75165,
		"LVL": 0.55565,
		"LYD": 1.2749,
		"MAD": 8.7953,
		"MDL": 11.95,
		"MGA": 2100,
		"MKD": 48.625,
		"MMK": 840.5,
		"MNT": 1322.5,
		"MOP": 7.9966,
		"MRO": 290.25,
		"MUR": 29.9,
		"MVR": 15.37,
		"MWK": 254.5,
		"MXN": 14.03635,
		"MYR": 3.155,
		"MZN": 27.950001,
		"NAD": 8.344,
		"NGN": 159.649994,
		"NIO": 23.334999,
		"NOK": 6.0286,
		"NPR": 89.610001,
		"NZD": 1.33193,
		"OMR": 0.38495,
		"PAB": 1,
		"PEN": 2.699,
		"PGK": 2.0121,
		"PHP": 43.700001,
		"PKR": 91.970001,
		"PLN": 3.4759,
		"PYG": 4505,
		"QAR": 3.6412,
		"RON": 3.5596,
		"RSD": 92.310501,
		"RUB": 31.738501,
		"RWF": 609.12323,
		"SAR": 3.7505,
		"SBD": 7.17768,
		"SCR": 14.2552,
		"SDG": 2.675,
		"SEK": 7.1814,
		"SGD": 1.27751,
		"SHP": 0.63785,
		"SLL": 4360,
		"SOS": 1625,
		"SRD": 3.275,
		"STD": 19505,
		"SVC": 8.7475,
		"SYP": 63.779999,
		"SZL": 8.374,
		"THB": 31.6,
		"TJS": 4.7633,
		"TMT": 2.861,
		"TND": 1.6017,
		"TOP": 1.787453,
		"TRY": 1.85015,
		"TTD": 6.38575,
		"TWD": 29.625999,
		"TZS": 1588.5,
		"UAH": 8.096,
		"UGX": 2500,
		"USD": 1,
		"UYU": 20.1,
		"UZS": 1868.650024,
		"VEF": 4.2927,
		"VND": 20845,
		"VUV": 95.550003,
		"WST": 2.35604,
		"XAF": 522.94574,
		"XCD": 2.7,
		"XDR": 0.658625,
		"XOF": 521.700012,
		"XPF": 93.550003,
		"YER": 214.604996,
		"ZAR": 8.3729,
		"ZMK": 5280,
		"ZWL": 322.355011
	}
}
