{
	"disclaimer": "This data is collected from various providers and provided free of charge for informational purposes only, with no guarantee whatsoever of accuracy, validity, availability or fitness for any purpose; use at your own risk. Other than that - have fun, and please share/watch/fork if you think data like this should be free!",
	"license": "Data collected from various providers with public-facing APIs; copyright may apply; not for resale; no warranties given.",
	"timestamp": 1329737664,
	"base": "USD",
	"rates": {
		"AED": 3.6732,
		"AFN": 49.279999,
		"ALL": 105.040001,
		"AMD": 389.26001,
		"ANG": 1.79,
		"AOA": 94.849998,
		"ARS": 4.35,
		"AUD": 0.927085,
		"AWG": 1.7899,
		"AZN": 0.7863,
		"BAM": 1.48,
		"BBD": 2,
		"BDT": 81.875,
		"BGN": 1.4806,
		"BHD": 0.37703,
		"BIF": 1310.5,
		"BMD": 1,
		"BND": 1.2521,
		"BOB": 6.91,
		"BRL": 1.7144,
		"BSD": 1,
		"BTN": 49.275002,
		"BWP": 7.2359,
		"BYR": 8280,
		"BZD": 1.9135,
		"CAD": 0.99133,
		"CDF": 915.566101,
		"CHF": 0.911715,
		"CLF": 0.02156,
		"CLP": 484.25,
		"CNY": 6.2945,
		"COP": 1780.5,
		"CRC": 509,
		"CUP": 1,
		"CVE": 83.699997,
		"CZK": 18.784651,
		"DJF": 179.5,
		"DKK": 5.6039,
		"DOP": 38.834999,
		"DZD": 75.540001,
		"EGP": 6.041,
		"ETB": 17.403601,
		"EUR": 0.753807,
		"FJD": 1.7481,
		"FKP": 0.6306,
		"GBP": 0.629729,
		"GEL": 1.65285,
		"GHS": 1.70025,
		"GIP": 0.6306,
		"GMD": 30.51,
		"GNF": 7100,
		"GTQ": 7.7715,
		"GYD": 202.949997,
		"HKD": 7.7543,
		"HNL": 19.055,
		"HRK": 5.7165,
		"HTG": 40.349998,
		"HUF": 216.449997,
		"IDR": 9033,
		"IEP": 0.594972,
		"ILS": 3.7227,
		"INR": 49.125,
		"IQD": 1165.5,
		"IRR": 12275,
		"ISK": 122.910004,
		"JMD": 86.419998,
		"JOD": 0.71,
		"JPY": 79.551003,
		"KES": 82.919998,
		"KGS": 46.736198,
		"KHR": 4010,
		"KMF": 371.661041,
		"KPW": 900,
		"KRW": 1123.5,
		"KWD": 0.27785,
		"KZT": 148.050003,
		"LAK": 7980.5,
		"LBP": 1505.5,
		"LKR": 118.25,
		"LRD": 73.75,
		"LSL": 7.65,
		"LTL": 2.60305,
		"LVL": 0.52695,
		"LYD": 1.2526,
		"MAD": 8.417,
		"MDL": 11.82,
		"MGA": 2180.5,
		"MKD": 47.200001,
		"MMK": 6.51,
		"MNT": 1326.780029,
		"MOP": 7.9868,
		"MRO": 293,
		"MUR": 29.280001,
		"MVR": 15.37,
		"MWK": 167.079605,
		"MXN": 12.6711,
		"MYR": 3.02075,
		"MZN": 27.25,
		"NAD": 7.659,
		"NGN": 157.300003,
		"NIO": 23.135,
		"NOK": 5.650275,
		"NPR": 78.699997,
		"NZD": 1.188354,
		"OMR": 0.38505,
		"PAB": 1,
		"PEN": 2.685,
		"PGK": 2.0661,
		"PHP": 42.560001,
		"PKR": 90.809998,
		"PLN": 3.14375,
		"PYG": 4445,
		"QAR": 3.6418,
		"RON": 3.2816,
		"RSD": 81.8405,
		"RUB": 29.738501,
		"RWF": 605.846558,
		"SAR": 3.7502,
		"SBD": 7.055977,
		"SCR": 14.00855,
		"SDG": 2.6769,
		"SEK": 6.64815,
		"SGD": 1.25145,
		"SHP": 0.6306,
		"SLL": 4400,
		"SOS": 1624.5,
		"SRD": 3.275,
		"STD": 18750,
		"SVC": 8.7475,
		"SYP": 57.450001,
		"SZL": 7.645,
		"THB": 30.76,
		"TJS": 4.7589,
		"TMT": 2.8725,
		"TND": 1.5033,
		"TOP": 1.689024,
		"TRY": 1.7368,
		"TTD": 6.3883,
		"TWD": 29.544001,
		"TZS": 1594,
		"UAH": 8.028,
		"UGX": 2321,
		"USD": 1,
		"UYU": 19.450001,
		"UZS": 1820.560059,
		"VEF": 4.2927,
		"VND": 20835,
		"VUV": 88.25,
		"WST": 2.280798,
		"XAF": 495.548096,
		"XCD": 2.7,
		"XDR": 0.647536,
		"XOF": 494.5,
		"XPF": 90.599998,
		"YER": 219.255005,
		"ZAR": 7.64535,
		"ZMK": 5200,
		"ZWD": 378.700012,
		"ZWL": 322.355011
	}
}
