{
  "disclaimer": "This data is collected from various providers and provided free of charge for informational purposes only, with no guarantee whatsoever of accuracy, validity, availability or fitness for any purpose; use at your own risk. Other than that - have fun, and please share/watch/fork if you think data like this should be free!",
  "license": "all code open-source under GPL v3 [http://www.opensource.org/licenses/GPL-3.0]. all data made available by various providers; copyright may apply; not for resale; no warranties given.",
  "timestamp": "954892800",
  "base": "USD",
  "rates": {
    "AED": "3.67242000",
    "ARS": "0.99980000",
    "AUD": "1.64929000",
    "BHD": "0.37599000",
    "BRL": "1.75500000",
    "CAD": "1.45031000",
    "CHF": "1.63610000",
    "CLP": "505.05051000",
    "COP": "1960.78442000",
    "CZK": "37.59399000",
    "DKK": "7.70416000",
    "DOP": "16.26016000",
    "EGP": "3.43171000",
    "EUR": "1.03859000",
    "GBP": "0.63130000",
    "HKD": "7.78816000",
    "HUF": "270.27026000",
    "IDR": "7692.30762000",
    "ILS": "4.05680000",
    "INR": "43.66812000",
    "JOD": "0.71000000",
    "JPY": "104.71205000",
    "KRW": "1111.11108000",
    "KWD": "0.30603000",
    "LBP": "1515.15149000",
    "MXN": "9.35454000",
    "MYR": "3.79939000",
    "NOK": "8.42460000",
    "NZD": "1.99481000",
    "PEN": "3.47584000",
    "PHP": "41.15226000",
    "PKR": "51.81347000",
    "SAR": "3.75094000",
    "SEK": "8.63558000",
    "SGD": "1.71201000",
    "THB": "37.86444000",
    "TWD": "30.48780000",
    "ZAR": "6.58761000",
    "IEP": "0.81820000"
  }
}