{
	"disclaimer": "This data is collected from various providers and provided free of charge for informational purposes only, with no guarantee whatsoever of accuracy, validity, availability, or fitness for any purpose; use at your own risk. Other than that, have fun! More info: http://openexchangerates.org/terms/",
	"license": "Data collected from various providers with public-facing APIs; copyright may apply; not for resale; no warranties given. Full license info: http://openexchangerates.org/license/",
	"timestamp": 992390400,
	"base": "USD",
	"rates": {
		"AED": 3.67242,
		"ARS": 0.9999,
		"AUD": 1.8879,
		"BHD": 0.37673,
		"BRL": 2.40668,
		"CAD": 1.51699,
		"CHF": 1.78952,
		"CLP": 609.7561,
		"CNY": 8.2779,
		"COP": 2325.58154,
		"CZK": 40,
		"DKK": 8.7184,
		"DOP": 16.20746,
		"EGP": 3.87447,
		"EUR": 1.1715,
		"GBP": 0.719,
		"HKD": 7.80031,
		"HUF": 294.11765,
		"IDR": 11111.11133,
		"IEP": 0.924,
		"ILS": 4.15973,
		"INR": 46.94836,
		"JOD": 0.71,
		"JPY": 122.10012,
		"KES": 78.3699,
		"KRW": 1298.70129,
		"KWD": 0.30836,
		"LBP": 1515.15149,
		"MXN": 9.07359,
		"MYR": 3.79939,
		"NOK": 9.35454,
		"NZD": 2.36412,
		"PEN": 3.51741,
		"PHP": 51.28205,
		"PKR": 62.89308,
		"SAR": 3.75094,
		"SEK": 10.83424,
		"SGD": 1.8159,
		"THB": 45.28985,
		"TWD": 34.36426,
		"USD": 1,
		"ZAR": 8.08407
	}
}
