{
	"disclaimer": "This data is collected from various providers and provided free of charge for informational purposes only, with no guarantee whatsoever of accuracy, validity, availability, or fitness for any purpose; use at your own risk. Other than that, have fun! More info: http://openexchangerates.org/terms/",
	"license": "Data collected from various providers with public-facing APIs; copyright may apply; not for resale; no warranties given. Full license info: http://openexchangerates.org/license/",
	"timestamp": 1024444800,
	"base": "USD",
	"rates": {
		"AED": 3.67242,
		"ARS": 3.50508,
		"AUD": 1.76869,
		"BHD": 0.37681,
		"BMD": 1,
		"BND": 1.7852,
		"BRL": 2.71437,
		"CAD": 1.54081,
		"CHF": 1.53749,
		"CLP": 671.14093,
		"CNY": 8.2774,
		"COP": 2380.95239,
		"CZK": 32.05128,
		"DKK": 7.76397,
		"DOP": 17.88909,
		"EGP": 4.63822,
		"EUR": 1.0453,
		"GBP": 0.6707,
		"HKD": 7.80031,
		"HRK": 7.65955,
		"HUF": 256.41025,
		"IDR": 8333.33398,
		"IEP": 0.87384,
		"ILS": 4.9554,
		"INR": 49.01961,
		"JOD": 0.709,
		"JPY": 123.76238,
		"KES": 78.30854,
		"KRW": 1234.56787,
		"KWD": 0.30502,
		"LBP": 1515.15149,
		"MXN": 9.72763,
		"MYR": 3.79939,
		"NOK": 7.70416,
		"NZD": 2.05128,
		"PEN": 3.46981,
		"PHP": 50.25126,
		"PKR": 60.24096,
		"SAR": 3.74953,
		"SEK": 9.48767,
		"SGD": 1.78511,
		"THB": 42.19409,
		"TWD": 34.12969,
		"UGX": 1797,
		"USD": 1,
		"UYU": 17.1775,
		"VUV": 135.82001,
		"XAF": 685.1084,
		"ZAR": 10.23541,
		"ZWD": 55.45
	}
}
