{
	"disclaimer": "This data is collected from various providers and provided free of charge for informational purposes only, with no guarantee whatsoever of accuracy, validity, availability, or fitness for any purpose; use at your own risk. Other than that, have fun! More info: http://openexchangerates.org/terms/",
	"license": "Data collected from various providers with public-facing APIs; copyright may apply; not for resale; no warranties given. Full license info: http://openexchangerates.org/license/",
	"timestamp": 1056585600,
	"base": "USD",
	"rates": {
		"AED": 3.67242,
		"ARS": 2.76007,
		"AUD": 1.4995,
		"BHD": 0.377,
		"BIF": 1075,
		"BMD": 1,
		"BND": 1.7555,
		"BRL": 2.88018,
		"CAD": 1.35389,
		"CHF": 1.34969,
		"CLP": 704.22534,
		"CNY": 8.2775,
		"COP": 2777.77783,
		"CZK": 27.24796,
		"DKK": 6.49351,
		"DOP": 26.5252,
		"EGP": 5.99161,
		"EUR": 0.875,
		"GBP": 0.6019,
		"HKD": 7.80031,
		"HRK": 6.5625,
		"HUF": 227.27274,
		"IDR": 8333.33398,
		"IEP": 0.79788,
		"ILS": 4.35161,
		"INR": 46.51163,
		"JOD": 0.709,
		"JPY": 119.33175,
		"KES": 74.62687,
		"KRW": 1190.4762,
		"KWD": 0.2999,
		"LBP": 1515.15149,
		"MXN": 10.4526,
		"MYR": 3.79939,
		"NOK": 7.22543,
		"NZD": 1.717,
		"PEN": 3.47826,
		"PHP": 53.47594,
		"PKR": 57.80347,
		"SAR": 3.74953,
		"SEK": 8.01925,
		"SGD": 1.75439,
		"THB": 41.47656,
		"TWD": 34.60208,
		"UGX": 2000,
		"USD": 1,
		"UYU": 26.415,
		"VUV": 120.18,
		"XAF": 574.16693,
		"ZAR": 7.5815,
		"ZMK": 4810,
		"ZWD": 824
	}
}
