{
  "disclaimer": "This data is collected from various providers and provided free of charge for informational purposes only, with no guarantee whatsoever of accuracy, validity, availability or fitness for any purpose; use at your own risk. Other than that - have fun, and please share/watch/fork if you think data like this should be free!",
  "license": "all code open-source under GPL v3 [http://www.opensource.org/licenses/GPL-3.0]. all data made available by various providers; copyright may apply; not for resale; no warranties given.",
  "timestamp": "1073433600",
  "base": "USD",
  "rates": {
    "AED": "3.67242000",
    "ARS": "2.85959000",
    "AUD": "1.30041000",
    "BHD": "0.37700000",
    "BRL": "2.87596000",
    "CAD": "1.29021000",
    "CHF": "1.23920000",
    "CLP": "564.97174000",
    "COP": "2777.77783000",
    "CZK": "25.38071000",
    "DKK": "5.87889000",
    "DOP": "33.89830000",
    "EGP": "6.17665000",
    "EUR": "0.79070000",
    "GBP": "0.54940000",
    "HKD": "7.76397000",
    "HUF": "204.08163000",
    "IDR": "8333.33398000",
    "ILS": "4.38212000",
    "INR": "45.45455000",
    "JOD": "0.70900000",
    "JPY": "106.15711000",
    "KRW": "1190.47620000",
    "KWD": "0.29470000",
    "LBP": "1515.15149000",
    "MXN": "10.90037000",
    "MYR": "3.79939000",
    "NOK": "6.77507000",
    "NZD": "1.49100000",
    "PEN": "3.46141000",
    "PHP": "55.24862000",
    "PKR": "57.14286000",
    "SAR": "3.74672000",
    "SEK": "7.17875000",
    "SGD": "1.69520000",
    "THB": "39.12363000",
    "TWD": "33.78378000",
    "ZAR": "6.55308000",
    "IEP": "0.79788000",
    "KES": "75.75758000",
    "CNY": "8.27720000",
    "BMD": "1.00000000",
    "BND": "1.69540000",
    "HRK": "6.10815000",
    "UGX": "1942.50000000",
    "UYU": "29.21500000",
    "VUV": "110.65000000",
    "XAF": "519.32312000",
    "ZWD": "824.00000000",
    "ZMK": "4765.00000000",
    "BIF": "1060.00000000"
  }
}