{
	"disclaimer": "This data is collected from various providers and provided free of charge for informational purposes only, with no guarantee whatsoever of accuracy, validity, availability, or fitness for any purpose; use at your own risk. Other than that, have fun! More info: http://openexchangerates.org/terms/",
	"license": "Data collected from various providers with public-facing APIs; copyright may apply; not for resale; no warranties given. Full license info: http://openexchangerates.org/license/",
	"timestamp": 1090454400,
	"base": "USD",
	"rates": {
		"AED": 3.67296,
		"ARS": 2.93997,
		"AUD": 1.39649,
		"BHD": 0.377,
		"BIF": 1060,
		"BMD": 1,
		"BND": 1.7157,
		"BRL": 3.027,
		"CAD": 1.316,
		"CHF": 1.2487,
		"CLP": 625,
		"CNY": 8.2765,
		"COP": 2631.57886,
		"CZK": 25.68713,
		"DKK": 6.06134,
		"DOP": 41.99916,
		"EGP": 6.19003,
		"EUR": 0.8163,
		"GBP": 0.5421,
		"HKD": 7.80031,
		"HRK": 6.02235,
		"HUF": 204.08163,
		"IDR": 9090.90918,
		"IEP": 0.79788,
		"ILS": 4.49438,
		"INR": 46.27487,
		"JOD": 0.709,
		"JPY": 109.76948,
		"KES": 79.8722,
		"KRW": 1162.79077,
		"KWD": 0.2947,
		"LBP": 1515.15149,
		"MXN": 11.42204,
		"MYR": 3.79954,
		"NOK": 6.91181,
		"NZD": 1.5562,
		"PEN": 3.427,
		"PHP": 55.99104,
		"PKR": 58.20722,
		"SAR": 3.75009,
		"SEK": 7.48951,
		"SGD": 1.71471,
		"THB": 41.06776,
		"TWD": 33.99048,
		"UGX": 1742.755,
		"USD": 1,
		"UYU": 29.435,
		"VUV": 114.1,
		"XAF": 535.19116,
		"ZAR": 6.03245,
		"ZMK": 4757.5,
		"ZWD": 5355.6499
	}
}
