{
	"disclaimer": "This data is collected from various providers and provided free of charge for informational purposes only, with no guarantee whatsoever of accuracy, validity, availability or fitness for any purpose; use at your own risk. Other than that - have fun, and please share/watch/fork if you think data like this should be free!",
	"license": "Data collected from various providers with public-facing APIs; copyright may apply; not for resale; no warranties given.",
	"timestamp": "1092787200",
	"base": "USD",
	"rates": {
		"AED": 3.67296,
		"ARS": 2.98,
		"AUD": 1.39659,
		"BHD": 0.377,
		"BIF": 1060,
		"BMD": 1,
		"BND": 1.71225,
		"BRL": 3.00797,
		"CAD": 1.3064,
		"CHF": 1.2458,
		"CLP": 636.94269,
		"CNY": 8.2767,
		"COP": 2631.57886,
		"CZK": 25.4907,
		"DKK": 6.02991,
		"DOP": 41.99916,
		"EGP": 6.23014,
		"EUR": 0.8114,
		"GBP": 0.5407,
		"HKD": 7.7997,
		"HRK": 5.97545,
		"HUF": 200.80321,
		"IDR": 9090.90918,
		"IEP": 0.79788,
		"ILS": 4.53515,
		"INR": 46.27487,
		"JOD": 0.709,
		"JPY": 109.28961,
		"KES": 80.5153,
		"KRW": 1162.79077,
		"KWD": 0.2947,
		"LBP": 1515.15149,
		"MXN": 11.35589,
		"MYR": 3.79983,
		"NOK": 6.74263,
		"NZD": 1.50509,
		"PEN": 3.40298,
		"PHP": 55.74136,
		"PKR": 58.68545,
		"RUB": 0.0342,
		"SAR": 3.75009,
		"SEK": 7.48111,
		"SGD": 1.71209,
		"THB": 41.49378,
		"TWD": 34.01361,
		"UGX": 1707.5,
		"USD": 1,
		"UYU": 28.435,
		"VUV": 113.37,
		"XAF": 531.74213,
		"ZAR": 6.48004,
		"ZMK": 4750,
		"ZWD": 5599.91016
	}
}
