{
	"disclaimer": "This data is collected from various providers and provided free of charge for informational purposes only, with no guarantee whatsoever of accuracy, validity, availability or fitness for any purpose; use at your own risk. Other than that - have fun, and please share/watch/fork if you think data like this should be free!",
	"license": "Data collected from various providers with public-facing APIs; copyright may apply; not for resale; no warranties given.",
	"timestamp": "1126656000",
	"base": "USD",
	"rates": {
		"AED": 3.67291,
		"ALL": 100.855,
		"ANG": 1.79,
		"ARS": 2.9188,
		"AUD": 1.2972,
		"AWG": 1.79,
		"BAM": 1.59195,
		"BBD": 2,
		"BHD": 0.377,
		"BIF": 1035.94995,
		"BMD": 1,
		"BND": 1.6783,
		"BRL": 2.3265,
		"BSD": 1,
		"BYR": 2154.5,
		"BZD": 1.97,
		"CAD": 1.1804,
		"CDF": 472.5,
		"CHF": 1.2584,
		"CLP": 536.48071,
		"CNY": 8.0912,
		"COP": 2288.32959,
		"CZK": 23.82995,
		"DKK": 6.60969,
		"DOP": 30.70027,
		"EGP": 5.76821,
		"ETB": 8.71565,
		"EUR": 0.8147,
		"GBP": 0.5485,
		"GMD": 27.85,
		"GNF": 3930,
		"GTQ": 7.6,
		"HKD": 7.75928,
		"HNL": 18.86,
		"HRK": 6.03855,
		"HTG": 41.4,
		"HUF": 199.68051,
		"IDR": 10000,
		"IEP": 0.79788,
		"ILS": 4.51779,
		"INR": 43.90008,
		"IRR": 9022,
		"JMD": 62.525,
		"JOD": 0.7085,
		"JPY": 110.36309,
		"KES": 74.10152,
		"KRW": 1025.64099,
		"KWD": 0.2919,
		"LBP": 1503.7594,
		"LSL": 6.35625,
		"MOP": 7.9939,
		"MRO": 268.17001,
		"MUR": 29.59,
		"MVR": 12.8,
		"MWK": 124.16,
		"MXN": 10.81502,
		"MYR": 3.7682,
		"NAD": 6.35625,
		"NGN": 131.85001,
		"NIO": 16.37,
		"NOK": 6.349,
		"NPR": 70.152,
		"NZD": 1.413,
		"PAB": 1,
		"PEN": 3.291,
		"PHP": 55.91903,
		"PKR": 59.78001,
		"PYG": 6125,
		"RON": 2.8406,
		"RUB": 0.03534,
		"RWF": 542.75,
		"SAR": 3.75009,
		"SBD": 7.27513,
		"SCR": 5.52065,
		"SEK": 7.591,
		"SGD": 1.6783,
		"SLL": 2902.5249,
		"SVC": 8.752,
		"SZL": 6.35625,
		"THB": 40.87973,
		"TOP": 1.95134,
		"TRY": 1.3415,
		"TTD": 6.2425,
		"TWD": 32.76969,
		"UGX": 1852.5,
		"USD": 1,
		"UYU": 24.135,
		"VUV": 110.875,
		"WST": 2.69683,
		"XAF": 533.90613,
		"XCD": 2.7,
		"XOF": 533.90613,
		"XPF": 97.0617,
		"YER": 192.83,
		"ZAR": 6.34711,
		"ZMK": 4315,
		"ZWD": 26000.17969
	}
}
