{
  "disclaimer": "This data is collected from various providers and provided free of charge for informational purposes only, with no guarantee whatsoever of accuracy, validity, availability or fitness for any purpose; use at your own risk. Other than that - have fun, and please share/watch/fork if you think data like this should be free!",
  "license": "all code open-source under GPL v3 [http://www.opensource.org/licenses/GPL-3.0]. all data made available by various providers; copyright may apply; not for resale; no warranties given.",
  "timestamp": "1108512000",
  "base": "USD",
  "rates": {
    "AED": "3.67282000",
    "ARS": "2.89001000",
    "AUD": "1.27371000",
    "BHD": "0.37700000",
    "BRL": "2.59619000",
    "CAD": "1.23640000",
    "CHF": "1.18730000",
    "CLP": "568.18182000",
    "COP": "2325.58154000",
    "CZK": "23.08936000",
    "DKK": "5.70483000",
    "DOP": "27.50275000",
    "EGP": "5.81159000",
    "EUR": "0.76720000",
    "GBP": "0.53020000",
    "HKD": "7.79909000",
    "HUF": "187.61726000",
    "IDR": "9090.90918000",
    "ILS": "4.36681000",
    "INR": "43.66812000",
    "JOD": "0.70907000",
    "JPY": "105.37408000",
    "KRW": "1020.40814000",
    "KWD": "0.29190000",
    "LBP": "1515.15149000",
    "MXN": "11.15076000",
    "MYR": "3.79983000",
    "NOK": "6.40615000",
    "NZD": "1.39980000",
    "PEN": "3.25998000",
    "PHP": "55.03578000",
    "PKR": "58.41122000",
    "SAR": "3.75009000",
    "SEK": "6.96718000",
    "SGD": "1.64029000",
    "THB": "38.37299000",
    "TWD": "31.55569000",
    "ZAR": "5.95274000",
    "IEP": "0.79788000",
    "KES": "76.68712000",
    "CNY": "8.27650000",
    "BMD": "1.00000000",
    "BND": "1.64135000",
    "HRK": "5.77590000",
    "UGX": "1717.00000000",
    "UYU": "24.63500000",
    "VUV": "107.01000000",
    "XAF": "503.42059000",
    "ZWD": "6048.45996000",
    "ZMK": "4765.00000000",
    "BIF": "1078.65002000",
    "RUB": "0.03570000",
    "ALL": "97.55000000",
    "ANG": "1.79000000",
    "AWG": "1.79000000",
    "BAM": "1.50105000",
    "BBD": "2.00000000",
    "BSD": "1.00000000",
    "BYR": "2169.00000000",
    "BZD": "1.98000000",
    "CDF": "473.00000000",
    "ETB": "8.69840000",
    "GMD": "29.40000000",
    "GNF": "2842.00000000",
    "GTQ": "7.72500000",
    "HNL": "18.73000000",
    "HTG": "36.50000000",
    "IRR": "8853.00000000",
    "SVC": "8.75200000",
    "SZL": "5.96875000",
    "TTD": "6.28280000",
    "XCD": "2.70000000",
    "XOF": "503.42059000",
    "XPF": "91.51955000",
    "YER": "187.14000000",
    "JMD": "61.35000000",
    "MOP": "8.03350000",
    "MRO": "263.20999000",
    "MUR": "28.62000000",
    "MVR": "12.80000000",
    "MWK": "108.05000000",
    "NAD": "5.96875000",
    "NGN": "133.00000000",
    "NIO": "16.23000000",
    "NPR": "69.90400000",
    "PAB": "1.00000000",
    "PYG": "6345.00000000",
    "RWF": "551.25000000",
    "SCR": "5.52065000",
    "SLL": "2500.00000000",
    "LSL": "5.96875000",
    "SBD": "7.27515000",
    "TOP": "1.90370000",
    "WST": "2.67345000",
    "TRY": "1.31350000"
  }
}