{
  "disclaimer": "This data is collected from various providers and provided free of charge for informational purposes only, with no guarantee whatsoever of accuracy, validity, availability or fitness for any purpose; use at your own risk. Other than that - have fun, and please share/watch/fork if you think data like this should be free!",
  "license": "all code open-source under GPL v3 [http://www.opensource.org/licenses/GPL-3.0]. all data made available by various providers; copyright may apply; not for resale; no warranties given.",
  "timestamp": "1158624000",
  "base": "USD",
  "rates": {
    "AED": "3.67300000",
    "ARS": "3.09820000",
    "AUD": "1.33000000",
    "BHD": "0.37700000",
    "BRL": "2.15700000",
    "CAD": "1.12770000",
    "CHF": "1.25120000",
    "CLP": "537.05695000",
    "COP": "2398.08154000",
    "CZK": "22.45022000",
    "DKK": "5.89091000",
    "DOP": "32.85043000",
    "EGP": "5.73250000",
    "EUR": "0.78880000",
    "GBP": "0.53150000",
    "HKD": "7.78610000",
    "HUF": "215.74973000",
    "IDR": "9174.31152000",
    "ILS": "4.34460000",
    "INR": "46.01086000",
    "JOD": "0.70850000",
    "JPY": "117.56407000",
    "KRW": "952.38092000",
    "KWD": "0.28920000",
    "LBP": "1512.85925000",
    "MXN": "10.95914000",
    "MYR": "3.68151000",
    "NOK": "6.52690000",
    "NZD": "1.51810000",
    "PEN": "3.24500000",
    "PHP": "50.03002000",
    "PKR": "60.15038000",
    "SAR": "3.75030000",
    "SEK": "7.25858000",
    "SGD": "1.59180000",
    "THB": "37.78004000",
    "TWD": "32.89041000",
    "ZAR": "7.37300000",
    "IEP": "0.79788000",
    "KES": "72.70084000",
    "CNY": "7.94100000",
    "BMD": "0.99750000",
    "BND": "1.58520000",
    "HRK": "5.87110000",
    "UGX": "1855.00000000",
    "UYU": "23.90000000",
    "VUV": "111.45000000",
    "XAF": "509.16501000",
    "ZWD": "253.89999000",
    "ZMK": "4050.00000000",
    "BIF": "980.00000000",
    "RUB": "0.03731000",
    "ALL": "101.49000000",
    "ANG": "1.78250000",
    "AWG": "1.79000000",
    "BAM": "1.54565000",
    "BBD": "1.99500000",
    "BSD": "0.99750000",
    "BYR": "2151.00000000",
    "BZD": "1.98500000",
    "CDF": "431.50000000",
    "ETB": "8.73620000",
    "GMD": "28.00000000",
    "GNF": "5550.00000000",
    "GTQ": "7.61200000",
    "HNL": "18.89000000",
    "HTG": "38.40000000",
    "IRR": "9195.00000000",
    "SVC": "8.75000000",
    "SZL": "7.39500000",
    "TTD": "6.25050000",
    "XCD": "2.68750000",
    "XOF": "517.34998000",
    "XPF": "97.05000000",
    "YER": "195.80000000",
    "JMD": "65.75000000",
    "MOP": "8.01890000",
    "MRO": "266.64999000",
    "MUR": "33.00000000",
    "MVR": "12.80000000",
    "MWK": "136.45000000",
    "NAD": "7.31400000",
    "NGN": "128.25000000",
    "NIO": "17.18000000",
    "NPR": "71.50000000",
    "PAB": "1.00000000",
    "PYG": "5730.00000000",
    "RWF": "551.96997000",
    "SCR": "5.41750000",
    "SLL": "3002.00000000",
    "LSL": "7.39500000",
    "SBD": "7.52944000",
    "TOP": "2.01007000",
    "WST": "2.81746000",
    "TRY": "1.46960000",
    "RON": "2.77300000",
    "STD": "6835.00000000",
    "IQD": "1474.59998000"
  }
}