{
	"disclaimer": "This data is collected from various providers and provided free of charge for informational purposes only, with no guarantee whatsoever of accuracy, validity, availability or fitness for any purpose; use at your own risk. Other than that - have fun, and please share/watch/fork if you think data like this should be free!",
	"license": "Data collected from various providers with public-facing APIs; copyright may apply; not for resale; no warranties given.",
	"timestamp": "1156723200",
	"base": "USD",
	"rates": {
		"AED": 3.6727,
		"ALL": 101.49,
		"ANG": 1.78,
		"ARS": 3.0963,
		"AUD": 1.3165,
		"AWG": 1.79,
		"BAM": 1.52955,
		"BBD": 1.995,
		"BHD": 0.377,
		"BIF": 980,
		"BMD": 0.9975,
		"BND": 1.5852,
		"BRL": 2.1443,
		"BSD": 0.9975,
		"BYR": 2151,
		"BZD": 1.985,
		"CAD": 1.1108,
		"CDF": 431.5,
		"CHF": 1.2354,
		"CLP": 537.34552,
		"CNY": 7.973,
		"COP": 2398.08154,
		"CZK": 22.02013,
		"DKK": 5.83209,
		"DOP": 32.73001,
		"EGP": 5.72751,
		"ETB": 8.7362,
		"EUR": 0.782,
		"GBP": 0.5276,
		"GMD": 28,
		"GNF": 5550,
		"GTQ": 7.6002,
		"HKD": 7.77901,
		"HNL": 18.89,
		"HRK": 5.7164,
		"HTG": 38.4,
		"HUF": 216.21622,
		"IDR": 9090.90918,
		"IEP": 0.79788,
		"ILS": 4.406,
		"INR": 46.47056,
		"IQD": 1477.59998,
		"IRR": 9189,
		"JMD": 66.075,
		"JOD": 0.7085,
		"JPY": 117.12345,
		"KES": 72.40081,
		"KRW": 963.39111,
		"KWD": 0.2892,
		"LBP": 1501.50146,
		"LSL": 7.1125,
		"MOP": 8.013,
		"MRO": 266.64999,
		"MUR": 32.75,
		"MVR": 12.78,
		"MWK": 136.05,
		"MXN": 10.87595,
		"MYR": 3.6795,
		"NAD": 7.193,
		"NGN": 128.25,
		"NIO": 17.18,
		"NOK": 6.28599,
		"NPR": 71.5,
		"NZD": 1.5672,
		"PAB": 1,
		"PEN": 3.247,
		"PHP": 51.11952,
		"PKR": 59.98081,
		"PYG": 5730,
		"RON": 2.7574,
		"RUB": 0.03735,
		"RWF": 551.96997,
		"SAR": 3.7503,
		"SBD": 7.29299,
		"SCR": 5.4175,
		"SEK": 7.23788,
		"SGD": 1.5785,
		"SLL": 2980,
		"STD": 6835,
		"SVC": 8.75,
		"SZL": 7.165,
		"THB": 37.66053,
		"TOP": 2.0143,
		"TRY": 1.4875,
		"TTD": 6.2505,
		"TWD": 32.90989,
		"UGX": 1858,
		"USD": 1,
		"UYU": 23.9,
		"VUV": 111.3,
		"WST": 2.83745,
		"XAF": 509.16501,
		"XCD": 2.685,
		"XOF": 512.90002,
		"XPF": 93.9,
		"YER": 195.75,
		"ZAR": 7.15999,
		"ZMK": 3895,
		"ZWD": 253.89999
	}
}
