{
	"disclaimer": "This data is collected from various providers and provided free of charge for informational purposes only, with no guarantee whatsoever of accuracy, validity, availability, or fitness for any purpose; use at your own risk. Other than that, have fun! More info: http://openexchangerates.org/terms/",
	"license": "Data collected from various providers with public-facing APIs; copyright may apply; not for resale; no warranties given. Full license info: http://openexchangerates.org/license/",
	"timestamp": 1169596800,
	"base": "USD",
	"rates": {
		"AED": 3.67291,
		"ALL": 93.08,
		"ANG": 1.78,
		"ARS": 3.083,
		"AUD": 1.2809,
		"AWG": 1.7905,
		"BAM": 1.5109,
		"BBD": 1.995,
		"BHD": 0.377,
		"BIF": 1013.97498,
		"BMD": 1.00125,
		"BND": 1.54295,
		"BRL": 2.1287,
		"BSD": 0.9975,
		"BYR": 2145,
		"BZD": 1.985,
		"CAD": 1.179,
		"CDF": 540,
		"CHF": 1.2487,
		"CLP": 539.37433,
		"CNY": 7.7724,
		"COP": 2252.2522,
		"CZK": 21.65018,
		"DKK": 5.75199,
		"DOP": 33.45041,
		"EGP": 5.70552,
		"ETB": 8.7498,
		"EUR": 0.7716,
		"GBP": 0.5083,
		"GMD": 27.825,
		"GNF": 5555,
		"GTQ": 7.67,
		"HKD": 7.80372,
		"HNL": 18.915,
		"HRK": 5.6907,
		"HTG": 37.55,
		"HUF": 195.77135,
		"IDR": 9090.90918,
		"IEP": 0.79788,
		"ILS": 4.2335,
		"INR": 44.23996,
		"IQD": 1294.80005,
		"IRR": 9230,
		"JMD": 67.275,
		"JOD": 0.7085,
		"JPY": 120.94823,
		"KES": 70.34822,
		"KRW": 935.45367,
		"KWD": 0.2892,
		"LBP": 1510.57397,
		"LSL": 7.105,
		"MOP": 8.0339,
		"MRO": 267.04999,
		"MUR": 33.35,
		"MVR": 12.8,
		"MWK": 139.05,
		"MXN": 10.93853,
		"MYR": 3.5,
		"NAD": 7.137,
		"NGN": 128.7,
		"NIO": 17.77,
		"NOK": 6.35231,
		"NPR": 69.75,
		"NZD": 1.443,
		"PAB": 1,
		"PEN": 3.193,
		"PHP": 48.84959,
		"PKR": 60.84946,
		"PYG": 5301,
		"RON": 2.6132,
		"RUB": 0.03767,
		"RWF": 549.81,
		"SAR": 3.7508,
		"SBD": 7.06097,
		"SCR": 5.4468,
		"SEK": 7.01198,
		"SGD": 1.5359,
		"SLL": 3000,
		"STD": 6680,
		"SVC": 8.7525,
		"SZL": 7.105,
		"THB": 35.20011,
		"TOP": 2.02861,
		"TRY": 1.4155,
		"TTD": 6.2505,
		"TWD": 32.86987,
		"UGX": 1760,
		"USD": 1,
		"UYU": 24.45,
		"VUV": 106.05,
		"WST": 2.75534,
		"XAF": 492.64499,
		"XCD": 2.6875,
		"XOF": 505.89999,
		"XPF": 92.55,
		"YER": 195.7,
		"ZAR": 7.14602,
		"ZMK": 4295,
		"ZWD": 252.89999
	}
}
