{
	"disclaimer": "This data is collected from various providers and provided free of charge for informational purposes only, with no guarantee whatsoever of accuracy, validity, availability or fitness for any purpose; use at your own risk. Other than that - have fun, and please share/watch/fork if you think data like this should be free!",
	"license": "Data collected from various providers with public-facing APIs; copyright may apply; not for resale; no warranties given.",
	"timestamp": "1219795200",
	"base": "USD",
	"rates": {
		"AED": 3.6738,
		"ALL": 82.7,
		"ANG": 1.775,
		"ARS": 3.025,
		"AUD": 1.1665,
		"AWG": 1.7905,
		"BAM": 1.3319,
		"BBD": 1.995,
		"BHD": 0.377,
		"BIF": 1048.35999,
		"BMD": 1.001,
		"BND": 1.5397,
		"BRL": 1.621,
		"BSD": 0.9975,
		"BYR": 2112,
		"BZD": 1.9698,
		"CAD": 1.0482,
		"CDF": 530,
		"CHF": 1.0982,
		"CLP": 519.48053,
		"CNY": 6.842,
		"COP": 1893.93933,
		"CZK": 16.77993,
		"DKK": 5.07099,
		"DOP": 34.96993,
		"EGP": 5.383,
		"ETB": 8.8844,
		"EUR": 0.6797,
		"FJD": 1.5953,
		"GBP": 0.5455,
		"GHS": 1.155,
		"GMD": 27.3,
		"GNF": 4575,
		"GTQ": 7.4115,
		"HKD": 7.8125,
		"HNL": 18.89,
		"HRK": 4.9144,
		"HTG": 37.9,
		"HUF": 161.29031,
		"IDR": 9174.31152,
		"IEP": 0.79788,
		"ILS": 3.57399,
		"INR": 43.85965,
		"IQD": 1185.5,
		"IRR": 9585,
		"JMD": 71.25,
		"JOD": 0.7086,
		"JPY": 109.64912,
		"KES": 68.97027,
		"KRW": 1084.59875,
		"KWD": 0.2676,
		"LBP": 1508.29565,
		"LSL": 7.785,
		"MOP": 8.0125,
		"MRO": 226.75,
		"MUR": 28.4,
		"MVR": 12.79,
		"MWK": 142.55,
		"MXN": 10.14199,
		"MYR": 3.3795,
		"NAD": 7.7545,
		"NGN": 118.525,
		"NIO": 17.77,
		"NOK": 5.3749,
		"NPR": 69.75,
		"NZD": 1.4266,
		"PAB": 1,
		"PEN": 2.956,
		"PGK": 2.574,
		"PHP": 45.66002,
		"PKR": 75.75758,
		"PYG": 3982.5,
		"RON": 2.413,
		"RUB": 0.04056,
		"RWF": 547.40002,
		"SAR": 3.7509,
		"SBD": 7.68592,
		"SCR": 8.049,
		"SEK": 6.39259,
		"SGD": 1.4198,
		"SLL": 2965,
		"STD": 14400,
		"SVC": 8.752,
		"SZL": 7.785,
		"THB": 34.25009,
		"TOP": 1.91405,
		"TRY": 1.191,
		"TTD": 6.1005,
		"TWD": 31.54972,
		"UGX": 1635.5,
		"USD": 1,
		"UYU": 19.35,
		"VUV": 95.05,
		"WST": 2.50352,
		"XAF": 506.10001,
		"XCD": 2.6705,
		"XOF": 443.5,
		"XPF": 80.65,
		"YER": 199.5,
		"ZAR": 7.75188,
		"ZMK": 3535.5,
		"ZWD": 29999.5
	}
}
