{
	"disclaimer": "This data is collected from various providers and provided free of charge for informational purposes only, with no guarantee whatsoever of accuracy, validity, availability, or fitness for any purpose; use at your own risk. Other than that, have fun! More info: http://openexchangerates.org/terms/",
	"license": "Data collected from various providers with public-facing APIs; copyright may apply; not for resale; no warranties given. Full license info: http://openexchangerates.org/license/",
	"timestamp": 1200873600,
	"base": "USD",
	"rates": {
		"AED": 3.673,
		"ALL": 83.1425,
		"ANG": 1.775,
		"ARS": 3.153,
		"AUD": 1.1391,
		"AWG": 1.7905,
		"BAM": 1.33765,
		"BBD": 1.995,
		"BHD": 0.3754,
		"BIF": 1048.35999,
		"BMD": 1.001,
		"BND": 1.5397,
		"BRL": 1.781,
		"BSD": 0.9975,
		"BYR": 2149.3501,
		"BZD": 1.975,
		"CAD": 1.0282,
		"CDF": 530,
		"CHF": 1.099,
		"CLP": 476.19049,
		"CNY": 7.247,
		"COP": 1964.6366,
		"CZK": 17.9501,
		"DKK": 5.0965,
		"DOP": 33.74958,
		"EGP": 5.49499,
		"ETB": 8.8844,
		"EUR": 0.6839,
		"GBP": 0.5113,
		"GMD": 27.3,
		"GNF": 4290,
		"GTQ": 7.7015,
		"HKD": 7.80652,
		"HNL": 18.89,
		"HRK": 5.017,
		"HTG": 37.9,
		"HUF": 175.87056,
		"IDR": 10000,
		"IEP": 0.79788,
		"ILS": 3.772,
		"INR": 39.22492,
		"IQD": 1205,
		"IRR": 9235.5,
		"JMD": 71.35,
		"JOD": 0.7087,
		"JPY": 106.66667,
		"KES": 68.89899,
		"KRW": 942.50708,
		"KWD": 0.2729,
		"LBP": 1510.57397,
		"LSL": 6.935,
		"MOP": 8.0125,
		"MRO": 247.05,
		"MUR": 28.75,
		"MVR": 12.795,
		"MWK": 137.55,
		"MXN": 10.915,
		"MYR": 3.271,
		"NAD": 7.0065,
		"NGN": 128.10001,
		"NIO": 17.77,
		"NOK": 5.47259,
		"NPR": 69.75,
		"NZD": 1.3161,
		"PAB": 1,
		"PEN": 2.965,
		"PHP": 40.6901,
		"PKR": 62.22001,
		"PYG": 5205,
		"RON": 2.525,
		"RUB": 0.04081,
		"RWF": 548.48999,
		"SAR": 3.7497,
		"SBD": 7.17768,
		"SCR": 7.992,
		"SEK": 6.44118,
		"SGD": 1.4384,
		"SLL": 2975,
		"STD": 14085,
		"SVC": 8.75,
		"SZL": 6.935,
		"THB": 30.82044,
		"TOP": 1.87107,
		"TRY": 1.1883,
		"TTD": 6.2505,
		"TWD": 32.36037,
		"UGX": 1700.5,
		"USD": 1,
		"UYU": 24.35,
		"VUV": 95,
		"WST": 2.53977,
		"XAF": 506.10001,
		"XCD": 2.685,
		"XOF": 447.75,
		"XPF": 82.15,
		"YER": 198.2,
		"ZAR": 7.05761,
		"ZMK": 3705.5,
		"ZWD": 29999
	}
}
