{
	"disclaimer": "This data is collected from various providers and provided free of charge for informational purposes only, with no guarantee whatsoever of accuracy, validity, availability, or fitness for any purpose; use at your own risk. Other than that, have fun! More info: http://openexchangerates.org/terms/",
	"license": "Data collected from various providers with public-facing APIs; copyright may apply; not for resale; no warranties given. Full license info: http://openexchangerates.org/license/",
	"timestamp": 1235001600,
	"base": "USD",
	"rates": {
		"AED": 3.6732,
		"ALL": 102.82,
		"ANG": 1.775,
		"ARS": 3.53299,
		"AUD": 1.5494,
		"AWG": 1.7905,
		"BAM": 1.55,
		"BBD": 1.995,
		"BHD": 0.377,
		"BIF": 1048.35999,
		"BMD": 1.001,
		"BND": 1.5397,
		"BRL": 2.3575,
		"BSD": 0.9975,
		"BYR": 2831,
		"BZD": 1.975,
		"CAD": 1.2555,
		"CDF": 530,
		"CHF": 1.1733,
		"CLP": 608.27252,
		"CNY": 6.8398,
		"COP": 2564.10254,
		"CZK": 22.78008,
		"DKK": 5.87541,
		"DOP": 35.5505,
		"EGP": 5.59901,
		"ETB": 8.8844,
		"EUR": 0.7884,
		"FJD": 1.8519,
		"GBP": 0.6992,
		"GHS": 1.375,
		"GMD": 27.3,
		"GNF": 4955,
		"GTQ": 7.9165,
		"HKD": 7.755,
		"HNL": 18.89,
		"HRK": 5.9002,
		"HTG": 37.9,
		"HUF": 239.23445,
		"IDR": 12048.19238,
		"IEP": 0.79788,
		"ILS": 4.14669,
		"INR": 49.61056,
		"IQD": 1160.30005,
		"IRR": 9592.5,
		"JMD": 90.5,
		"JOD": 0.7091,
		"JPY": 94.40196,
		"KES": 79.64954,
		"KRW": 1451.37878,
		"KWD": 0.2936,
		"LBP": 1501.50146,
		"LSL": 10.1755,
		"MOP": 8.0125,
		"MRO": 253.25,
		"MUR": 33.95,
		"MVR": 12.785,
		"MWK": 140.55,
		"MXN": 14.68256,
		"MYR": 3.655,
		"NAD": 10.2015,
		"NGN": 149.25,
		"NIO": 17.77,
		"NOK": 6.87578,
		"NPR": 69.75,
		"NZD": 1.9519,
		"PAB": 1,
		"PEN": 3.27499,
		"PGK": 2.7093,
		"PHP": 47.84918,
		"PKR": 79.75754,
		"PYG": 5075,
		"RON": 3.3672,
		"RUB": 0.02791,
		"RWF": 567.09998,
		"SAR": 3.7506,
		"SBD": 7.95536,
		"SCR": 16.745,
		"SEK": 8.70322,
		"SGD": 1.5258,
		"SLL": 3080,
		"STD": 15286.7002,
		"SVC": 8.7518,
		"SZL": 10.1755,
		"THB": 35.56061,
		"TOP": 2.23992,
		"TRY": 1.6868,
		"TTD": 6.2605,
		"TWD": 34.59011,
		"UGX": 1960.5,
		"USD": 1,
		"UYU": 23.3,
		"VUV": 118.05,
		"WST": 3.05228,
		"XAF": 506.10001,
		"XCD": 2.6605,
		"XOF": 521.54999,
		"XPF": 94.85,
		"YER": 199.75,
		"ZAR": 10.04833,
		"ZMK": 5795,
		"ZWD": 29999.5
	}
}
