{
	"disclaimer": "This data is collected from various providers and provided free of charge for informational purposes only, with no guarantee whatsoever of accuracy, validity, availability or fitness for any purpose; use at your own risk. Other than that - have fun, and please share/watch/fork if you think data like this should be free!",
	"license": "Data collected from various providers with public-facing APIs; copyright may apply; not for resale; no warranties given.",
	"timestamp": "1286928000",
	"base": "USD",
	"rates": {
		"AED": 3.67295,
		"ALL": 99.06,
		"ANG": 1.7919,
		"ARS": 3.95401,
		"AUD": 1.01,
		"AWG": 1.7905,
		"BAM": 1.40425,
		"BBD": 1.975,
		"BHD": 0.37701,
		"BIF": 1048.35999,
		"BMD": 1.0008,
		"BND": 1.309,
		"BRL": 1.6567,
		"BSD": 0.9975,
		"BYR": 2996,
		"BZD": 1.975,
		"CAD": 1.00355,
		"CDF": 905,
		"CHF": 0.95835,
		"CLP": 478.01147,
		"CNY": 6.66405,
		"COP": 1788.90881,
		"CZK": 17.50486,
		"DKK": 5.34171,
		"DOP": 37.22454,
		"EGP": 5.70301,
		"ETB": 8.8844,
		"EUR": 0.71644,
		"FJD": 1.8519,
		"GBP": 0.62919,
		"GHS": 1.43,
		"GMD": 27.125,
		"GNF": 6900,
		"GTQ": 8.0885,
		"HKD": 7.76006,
		"HNL": 18.92,
		"HRK": 5.2516,
		"HTG": 40.25,
		"HUF": 196.03999,
		"IDR": 8928.57129,
		"IEP": 0.79788,
		"ILS": 3.61,
		"INR": 44.32428,
		"IQD": 1169.20996,
		"IRR": 10505,
		"JMD": 88.53,
		"JOD": 0.70875,
		"JPY": 81.80628,
		"KES": 80.50233,
		"KRW": 1131.22168,
		"KWD": 0.2825,
		"LBP": 1501.50146,
		"LSL": 6.855,
		"MOP": 8.0125,
		"MRO": 285.25,
		"MUR": 29.85,
		"MVR": 12.8,
		"MWK": 153.5,
		"MXN": 12.36751,
		"MYR": 3.08775,
		"NAD": 6.8995,
		"NGN": 152.25,
		"NIO": 17.77,
		"NOK": 5.78989,
		"NPR": 69.75,
		"NZD": 1.3197,
		"PAB": 1.015,
		"PEN": 2.7885,
		"PGK": 2.578,
		"PHP": 43.33507,
		"PKR": 86.10298,
		"PYG": 4920,
		"RON": 3.0625,
		"RUB": 0.03321,
		"RWF": 585,
		"SAR": 3.75005,
		"SBD": 7.7939,
		"SCR": 12.252,
		"SEK": 6.6353,
		"SGD": 1.303,
		"SLL": 4020,
		"STD": 17575,
		"SVC": 8.7475,
		"SZL": 6.855,
		"THB": 29.84006,
		"TOP": 1.90131,
		"TRY": 1.4074,
		"TTD": 6.37,
		"TWD": 30.81189,
		"UGX": 2265,
		"USD": 1,
		"UYU": 20.15,
		"VUV": 93.35,
		"WST": 2.46951,
		"XAF": 506.10001,
		"XCD": 2.685,
		"XOF": 474.60001,
		"XPF": 86.625,
		"YER": 214.625,
		"ZAR": 6.821,
		"ZMK": 4750,
		"ZWD": 29999.5
	}
}
