{
	"disclaimer": "This data is collected from various providers and provided free of charge for informational purposes only, with no guarantee whatsoever of accuracy, validity, availability or fitness for any purpose; use at your own risk. Other than that - have fun, and please share/watch/fork if you think data like this should be free!",
	"license": "Data collected from various providers with public-facing APIs; copyright may apply; not for resale; no warranties given.",
	"timestamp": "1270512000",
	"base": "USD",
	"rates": {
		"AED": 3.67291,
		"ALL": 103.87,
		"ANG": 1.792,
		"ARS": 3.8775,
		"AUD": 1.07793,
		"AWG": 1.7905,
		"BAM": 1.46515,
		"BBD": 1.975,
		"BHD": 0.37699,
		"BIF": 1048.35999,
		"BMD": 0.9999,
		"BND": 1.3985,
		"BRL": 1.7605,
		"BSD": 0.9975,
		"BYR": 2976,
		"BZD": 1.975,
		"CAD": 1.0002,
		"CDF": 875,
		"CHF": 1.06915,
		"CLP": 520.02081,
		"CNY": 6.8305,
		"COP": 1912.0459,
		"CZK": 18.76489,
		"DKK": 5.55781,
		"DOP": 36.39937,
		"EGP": 5.50509,
		"ETB": 8.8844,
		"EUR": 0.7466,
		"FJD": 1.9327,
		"GBP": 0.65516,
		"GHS": 1.42,
		"GMD": 26.75,
		"GNF": 5008.2998,
		"GTQ": 7.981,
		"HKD": 7.76603,
		"HNL": 18.92,
		"HRK": 5.4374,
		"HTG": 40.25,
		"HUF": 197.98061,
		"IDR": 9009.00879,
		"IEP": 0.79788,
		"ILS": 3.6985,
		"INR": 44.36951,
		"IQD": 1168.55005,
		"IRR": 9900,
		"JMD": 88.85,
		"JOD": 0.70825,
		"JPY": 93.75586,
		"KES": 77.17836,
		"KRW": 1122.33447,
		"KWD": 0.28865,
		"LBP": 1501.50146,
		"LSL": 7.245,
		"MOP": 8.0125,
		"MRO": 263.25,
		"MUR": 30.75,
		"MVR": 12.795,
		"MWK": 151.3,
		"MXN": 12.24695,
		"MYR": 3.2225,
		"NAD": 7.2465,
		"NGN": 150,
		"NIO": 17.77,
		"NOK": 5.96388,
		"NPR": 69.75,
		"NZD": 1.41633,
		"PAB": 1.015,
		"PEN": 2.839,
		"PGK": 2.6392,
		"PHP": 44.87525,
		"PKR": 84.04774,
		"PYG": 4695,
		"RON": 3.0613,
		"RUB": 0.03409,
		"RWF": 573.5,
		"SAR": 3.75005,
		"SBD": 7.7636,
		"SCR": 11.716,
		"SEK": 7.20529,
		"SGD": 1.3965,
		"SLL": 3850,
		"STD": 18040,
		"SVC": 8.7475,
		"SZL": 7.235,
		"THB": 32.38027,
		"TOP": 1.93255,
		"TRY": 1.5063,
		"TTD": 6.41,
		"TWD": 31.59458,
		"UGX": 2085,
		"USD": 1,
		"UYU": 19.25,
		"VUV": 96.65,
		"WST": 2.56255,
		"XAF": 506.10001,
		"XCD": 2.695,
		"XOF": 486.20001,
		"XPF": 88.925,
		"YER": 203.75,
		"ZAR": 7.26501,
		"ZMK": 4705,
		"ZWD": 29999.5
	}
}
