{
	"disclaimer": "This data is collected from various providers and provided free of charge for informational purposes only, with no guarantee whatsoever of accuracy, validity, availability, or fitness for any purpose; use at your own risk. Other than that, have fun! More info: http://openexchangerates.org/terms/",
	"license": "Data collected from various providers with public-facing APIs; copyright may apply; not for resale; no warranties given. Full license info: http://openexchangerates.org/license/",
	"timestamp": 1271721600,
	"base": "USD",
	"rates": {
		"AED": 3.67291,
		"ALL": 102.87,
		"ANG": 1.792,
		"ARS": 3.8685,
		"AUD": 1.07308,
		"AWG": 1.7905,
		"BAM": 1.45,
		"BBD": 1.975,
		"BHD": 0.3771,
		"BIF": 1048.35999,
		"BMD": 0.9999,
		"BND": 1.379,
		"BRL": 1.7536,
		"BSD": 0.9975,
		"BYR": 2973,
		"BZD": 1.975,
		"CAD": 0.9988,
		"CDF": 880,
		"CHF": 1.06795,
		"CLP": 528.82074,
		"CNY": 6.83,
		"COP": 1953.125,
		"CZK": 18.82495,
		"DKK": 5.53639,
		"DOP": 36.42456,
		"EGP": 5.53269,
		"ETB": 8.8844,
		"EUR": 0.74408,
		"FJD": 1.9066,
		"GBP": 0.65018,
		"GHS": 1.415,
		"GMD": 26.25,
		"GNF": 5025,
		"GTQ": 7.9965,
		"HKD": 7.76385,
		"HNL": 18.92,
		"HRK": 5.3958,
		"HTG": 40.25,
		"HUF": 196.77292,
		"IDR": 9009.00879,
		"IEP": 0.79788,
		"ILS": 3.7325,
		"INR": 44.43457,
		"IQD": 1167.5,
		"IRR": 9895,
		"JMD": 88.62,
		"JOD": 0.70825,
		"JPY": 93.22271,
		"KES": 77.2499,
		"KRW": 1118.56824,
		"KWD": 0.2885,
		"LBP": 1501.50146,
		"LSL": 7.43,
		"MOP": 8.0125,
		"MRO": 266.25,
		"MUR": 30.95,
		"MVR": 12.8,
		"MWK": 151.52499,
		"MXN": 12.22001,
		"MYR": 3.209,
		"NAD": 7.4715,
		"NGN": 150.5,
		"NIO": 17.77,
		"NOK": 5.9027,
		"NPR": 69.75,
		"NZD": 1.40459,
		"PAB": 1.015,
		"PEN": 2.861,
		"PGK": 2.6882,
		"PHP": 44.52558,
		"PKR": 84.04774,
		"PYG": 4720,
		"RON": 3.0837,
		"RUB": 0.03434,
		"RWF": 573,
		"SAR": 3.75025,
		"SBD": 7.90497,
		"SCR": 12,
		"SEK": 7.14791,
		"SGD": 1.3752,
		"SLL": 3870,
		"STD": 18040,
		"SVC": 8.7475,
		"SZL": 7.433,
		"THB": 32.16986,
		"TOP": 1.92141,
		"TRY": 1.4872,
		"TTD": 6.37,
		"TWD": 31.43468,
		"UGX": 2085,
		"USD": 1,
		"UYU": 19.35,
		"VUV": 96.55,
		"WST": 2.56453,
		"XAF": 506.10001,
		"XCD": 2.685,
		"XOF": 486.54999,
		"XPF": 88.9,
		"YER": 203.8,
		"ZAR": 7.43262,
		"ZMK": 4710,
		"ZWD": 29999.5
	}
}
