{
	"disclaimer": "This data is collected from various providers and provided free of charge for informational purposes only, with no guarantee whatsoever of accuracy, validity, availability, or fitness for any purpose; use at your own risk. Other than that, have fun! More info: http://openexchangerates.org/terms/",
	"license": "Data collected from various providers with public-facing APIs; copyright may apply; not for resale; no warranties given. Full license info: http://openexchangerates.org/license/",
	"timestamp": 1273881600,
	"base": "USD",
	"rates": {
		"AED": 3.67305,
		"ALL": 109.79,
		"ANG": 1.792,
		"ARS": 3.89699,
		"AUD": 1.12886,
		"AWG": 1.7905,
		"BAM": 1.58165,
		"BBD": 1.975,
		"BHD": 0.377,
		"BIF": 1048.35999,
		"BMD": 0.9999,
		"BND": 1.3805,
		"BRL": 1.7705,
		"BSD": 0.9975,
		"BYR": 2991,
		"BZD": 1.975,
		"CAD": 1.03265,
		"CDF": 880,
		"CHF": 1.13315,
		"CLP": 534.18805,
		"CNY": 6.8325,
		"COP": 1956.94714,
		"CZK": 20.16983,
		"DKK": 6.01851,
		"DOP": 36.74984,
		"EGP": 5.60849,
		"ETB": 8.8844,
		"EUR": 0.80916,
		"FJD": 1.9539,
		"GBP": 0.68792,
		"GHS": 1.425,
		"GMD": 27.025,
		"GNF": 5025,
		"GTQ": 7.9985,
		"HKD": 7.78301,
		"HNL": 18.92,
		"HRK": 5.8573,
		"HTG": 40.25,
		"HUF": 222.51891,
		"IDR": 9174.31152,
		"IEP": 0.79788,
		"ILS": 3.77,
		"INR": 45.22431,
		"IQD": 1169.38,
		"IRR": 9945,
		"JMD": 88.53,
		"JOD": 0.70825,
		"JPY": 92.48127,
		"KES": 78.3024,
		"KRW": 1129.94348,
		"KWD": 0.2905,
		"LBP": 1501.50146,
		"LSL": 7.535,
		"MOP": 8.0125,
		"MRO": 267.25,
		"MUR": 32.05,
		"MVR": 12.8,
		"MWK": 152.05,
		"MXN": 12.58701,
		"MYR": 3.21,
		"NAD": 7.4315,
		"NGN": 150.75,
		"NIO": 17.77,
		"NOK": 6.2445,
		"NPR": 69.75,
		"NZD": 1.41343,
		"PAB": 1.015,
		"PEN": 2.8385,
		"PGK": 2.7495,
		"PHP": 45.12432,
		"PKR": 84.2531,
		"PYG": 4745,
		"RON": 3.3788,
		"RUB": 0.03297,
		"RWF": 578.625,
		"SAR": 3.75025,
		"SBD": 7.88002,
		"SCR": 12.104,
		"SEK": 7.74629,
		"SGD": 1.3876,
		"SLL": 3900,
		"STD": 18040,
		"SVC": 8.7475,
		"SZL": 7.515,
		"THB": 32.44015,
		"TOP": 1.9982,
		"TRY": 1.542,
		"TTD": 6.37,
		"TWD": 31.73495,
		"UGX": 2155,
		"USD": 1,
		"UYU": 19,
		"VUV": 97,
		"WST": 2.44835,
		"XAF": 506.10001,
		"XCD": 2.685,
		"XOF": 520.90002,
		"XPF": 95.5,
		"YER": 203.8,
		"ZAR": 7.57002,
		"ZMK": 4925,
		"ZWD": 29999.5
	}
}
