{
	"disclaimer": "This data is collected from various providers and provided free of charge for informational purposes only, with no guarantee whatsoever of accuracy, validity, availability or fitness for any purpose; use at your own risk. Other than that - have fun, and please share/watch/fork if you think data like this should be free!",
	"license": "Data collected from various providers with public-facing APIs; copyright may apply; not for resale; no warranties given.",
	"timestamp": "1310860800",
	"base": "USD",
	"rates": {
		"AED": 3.673,
		"ALL": 98.25,
		"ANG": 1.7635,
		"ARS": 4.12279,
		"AUD": 0.9391,
		"AWG": 1.7905,
		"BAM": 1.38535,
		"BBD": 1.9899,
		"BHD": 0.37696,
		"BIF": 1229.5,
		"BMD": 0.99995,
		"BND": 1.2187,
		"BRL": 1.5739,
		"BSD": 0.9998,
		"BYR": 3045,
		"BZD": 1.9599,
		"CAD": 0.95325,
		"CDF": 915,
		"CHF": 0.81275,
		"CLP": 462.5347,
		"CNY": 6.43385,
		"COP": 1745.20068,
		"CZK": 17.27504,
		"DKK": 5.26746,
		"DOP": 38.07058,
		"EGP": 5.95291,
		"ETB": 17.01645,
		"EUR": 0.70659,
		"FJD": 1.7461,
		"GBP": 0.61975,
		"GHS": 1.5125,
		"GMD": 27.845,
		"GNF": 6650,
		"GTQ": 7.736,
		"HKD": 7.79411,
		"HNL": 18.89345,
		"HRK": 5.25205,
		"HTG": 40.34395,
		"HUF": 190.51248,
		"IDR": 8547.00879,
		"IEP": 0.79788,
		"ILS": 3.42945,
		"INR": 44.47409,
		"IQD": 1168,
		"IRR": 10598.9502,
		"JMD": 85.46195,
		"JOD": 0.70905,
		"JPY": 79.10767,
		"KES": 89.75049,
		"KRW": 1058.20105,
		"KWD": 0.27395,
		"LBP": 1512.85925,
		"LSL": 6.905,
		"MOP": 8.02535,
		"MRO": 275.25,
		"MUR": 28.197,
		"MVR": 15.35995,
		"MWK": 151.53,
		"MXN": 11.74302,
		"MYR": 3.00675,
		"NAD": 6.8975,
		"NGN": 152.5,
		"NIO": 22.458,
		"NOK": 5.55451,
		"NPR": 71.334,
		"NZD": 1.18385,
		"PAB": 0.99971,
		"PEN": 2.74145,
		"PGK": 2.2472,
		"PHP": 42.94426,
		"PKR": 86.2069,
		"PYG": 3948.5,
		"RON": 3.0129,
		"RUB": 0.03562,
		"RWF": 596,
		"SAR": 3.75021,
		"SBD": 7.24012,
		"SCR": 12.24345,
		"SEK": 6.48976,
		"SGD": 1.2194,
		"SLL": 4365,
		"STD": 17350,
		"SVC": 8.74715,
		"SZL": 6.913,
		"THB": 30.077,
		"TOP": 1.72427,
		"TRY": 1.6507,
		"TTD": 6.4,
		"TWD": 28.89088,
		"UGX": 2575,
		"USD": 1,
		"UYU": 18.45,
		"VUV": 89,
		"WST": 2.29073,
		"XAF": 463.63,
		"XCD": 2.685,
		"XOF": 464.25,
		"XPF": 84.15,
		"YER": 213.8,
		"ZAR": 6.88444,
		"ZMK": 4839.5,
		"ZWD": 29999.5
	}
}
