{
  "disclaimer": "This data is collected from various providers and provided free of charge for informational purposes only, with no guarantee whatsoever of accuracy, validity, availability or fitness for any purpose; use at your own risk. Other than that - have fun, and please share/watch/fork if you think data like this should be free!",
  "license": "all code open-source under GPL v3 [http://www.opensource.org/licenses/GPL-3.0]. all data made available by various providers; copyright may apply; not for resale; no warranties given.",
  "timestamp": "1312070400",
  "base": "USD",
  "rates": {
    "AED": "3.67295000",
    "ARS": "4.13820000",
    "AUD": "0.90851000",
    "BHD": "0.37694000",
    "BRL": "1.54910000",
    "CAD": "0.95450000",
    "CHF": "0.78600000",
    "CLP": "456.82959000",
    "COP": "1776.19897000",
    "CZK": "16.79092000",
    "DKK": "5.17440000",
    "DOP": "38.04451000",
    "EGP": "5.95877000",
    "EUR": "0.69457000",
    "GBP": "0.60888000",
    "HKD": "7.79369000",
    "HUF": "187.33607000",
    "IDR": "8474.57617000",
    "ILS": "3.43395000",
    "INR": "44.10532000",
    "JOD": "0.70825000",
    "JPY": "76.71653000",
    "KRW": "1053.74072000",
    "KWD": "0.27293000",
    "LBP": "1512.85925000",
    "MXN": "11.73296000",
    "MYR": "2.96295000",
    "NOK": "5.37346000",
    "NZD": "1.13850000",
    "PEN": "2.73880000",
    "PHP": "42.19587000",
    "PKR": "86.60258000",
    "SAR": "3.75025000",
    "SEK": "6.27475000",
    "SGD": "1.20365000",
    "THB": "29.77963000",
    "TWD": "28.87920000",
    "ZAR": "6.68052000",
    "IEP": "0.79788000",
    "KES": "90.97525000",
    "CNY": "6.44045000",
    "BMD": "1.00005000",
    "BND": "1.20500000",
    "HRK": "5.16730000",
    "UGX": "2610.00000000",
    "UYU": "18.35000000",
    "VUV": "86.60000000",
    "XAF": "460.64499000",
    "ZWD": "29999.50000000",
    "ZMK": "4796.50000000",
    "BIF": "1229.50000000",
    "RUB": "0.03623000",
    "ALL": "97.48000000",
    "ANG": "1.76350000",
    "AWG": "1.79050000",
    "BAM": "1.36135000",
    "BBD": "2.00060000",
    "BSD": "0.99265000",
    "BYR": "3045.00000000",
    "BZD": "1.98605000",
    "CDF": "919.00000000",
    "ETB": "17.05245000",
    "GMD": "27.90500000",
    "GNF": "6705.00000000",
    "GTQ": "7.78610000",
    "HNL": "18.86095000",
    "HTG": "40.36345000",
    "IRR": "10572.45020000",
    "SVC": "8.75080000",
    "SZL": "6.72000000",
    "TTD": "6.37720000",
    "XCD": "2.68500000",
    "XOF": "458.85001000",
    "XPF": "83.72500000",
    "YER": "213.25000000",
    "JMD": "85.50795000",
    "MOP": "8.03070000",
    "MRO": "278.10001000",
    "MUR": "27.79750000",
    "MVR": "15.38995000",
    "MWK": "152.37000000",
    "NAD": "6.71145000",
    "NGN": "153.12000000",
    "NIO": "22.51050000",
    "NPR": "70.80350000",
    "PAB": "0.99998000",
    "PYG": "3805.00000000",
    "RWF": "599.99500000",
    "SCR": "12.23945000",
    "SLL": "4380.00000000",
    "LSL": "6.71500000",
    "SBD": "7.41758000",
    "TOP": "1.61744000",
    "WST": "2.18749000",
    "TRY": "1.69770000",
    "RON": "2.94910000",
    "STD": "17145.00000000",
    "IQD": "1168.02002000",
    "FJD": "1.72100000",
    "PGK": "2.22970000",
    "GHS": "1.51000000"
  }
}