{
	"disclaimer": "This data is collected from various providers and provided free of charge for informational purposes only, with no guarantee whatsoever of accuracy, validity, availability, or fitness for any purpose; use at your own risk. Other than that, have fun! More info: http://openexchangerates.org/terms/",
	"license": "Data collected from various providers with public-facing APIs; copyright may apply; not for resale; no warranties given. Full license info: http://openexchangerates.org/license/",
	"timestamp": 1336435253,
	"base": "USD",
	"rates": {
		"AED": 3.6732,
		"AFN": 48.299999,
		"ALL": 107.199997,
		"AMD": 392.130005,
		"ANG": 1.79,
		"AOA": 95.324997,
		"ARS": 4.433,
		"AUD": 0.978929,
		"AWG": 1.7901,
		"AZN": 0.786,
		"BAM": 1.50135,
		"BBD": 2,
		"BDT": 81.949997,
		"BGN": 1.5057,
		"BHD": 0.37705,
		"BIF": 1385.25,
		"BMD": 1,
		"BND": 1.2455,
		"BOB": 6.91,
		"BRL": 1.9204,
		"BSD": 1,
		"BTN": 52.904999,
		"BWP": 7.3827,
		"BYR": 8100,
		"BZD": 1.93,
		"CAD": 0.992515,
		"CDF": 924.531677,
		"CHF": 0.919905,
		"CLF": 0.02138,
		"CLP": 483.380005,
		"CNH": 6.2995,
		"CNY": 6.3088,
		"COP": 1758.199951,
		"CRC": 509,
		"CUP": 1,
		"CVE": 84.699997,
		"CZK": 19.199499,
		"DJF": 179.740005,
		"DKK": 5.69403,
		"DOP": 39,
		"DZD": 74.425003,
		"EGP": 6.0396,
		"ETB": 17.591,
		"EUR": 0.765714,
		"FJD": 1.8067,
		"FKP": 0.6175,
		"GBP": 0.617551,
		"GEL": 1.623,
		"GHS": 1.857,
		"GIP": 0.61755,
		"GMD": 29.690001,
		"GNF": 7042.5,
		"GTQ": 7.7945,
		"GYD": 203.199997,
		"HKD": 7.7629,
		"HNL": 19.055,
		"HRK": 5.74625,
		"HTG": 41.849998,
		"HUF": 219.725006,
		"IDR": 9263,
		"IEP": 0.603173,
		"ILS": 3.79735,
		"INR": 52.91,
		"IQD": 1165.5,
		"IRR": 12283,
		"ISK": 124.709999,
		"JMD": 86.800003,
		"JOD": 0.7095,
		"JPY": 79.927498,
		"KES": 83.18,
		"KGS": 46.970001,
		"KHR": 4038.300049,
		"KMF": 376.784698,
		"KPW": 900,
		"KRW": 1138.599976,
		"KWD": 0.27815,
		"KZT": 147.880005,
		"LAK": 8007.299805,
		"LBP": 1505.5,
		"LKR": 127.75,
		"LRD": 74.5,
		"LSL": 7.8094,
		"LTL": 2.64375,
		"LVL": 0.53545,
		"LYD": 1.2495,
		"MAD": 8.5265,
		"MDL": 11.85,
		"MGA": 2075,
		"MKD": 47.150002,
		"MMK": 824.5,
		"MNT": 1307.5,
		"MOP": 7.9958,
		"MRO": 290.75,
		"MUR": 29.129999,
		"MVR": 15.32,
		"MWK": 249.5,
		"MXN": 13.1539,
		"MYR": 3.0525,
		"MZN": 27.337999,
		"NAD": 7.824,
		"NGN": 157.25,
		"NIO": 23.275,
		"NOK": 5.7951,
		"NPR": 84.150002,
		"NZD": 1.254485,
		"OMR": 0.38555,
		"PAB": 1,
		"PEN": 2.641,
		"PGK": 2.0416,
		"PHP": 42.400002,
		"PKR": 90.82,
		"PLN": 3.20245,
		"PYG": 4290,
		"QAR": 3.6415,
		"RON": 3.3677,
		"RSD": 85.805496,
		"RUB": 30.0348,
		"RWF": 608.124878,
		"SAR": 3.7502,
		"SBD": 7.070963,
		"SCR": 14.1055,
		"SDG": 2.675,
		"SEK": 6.82045,
		"SGD": 1.245385,
		"SHP": 0.61755,
		"SLL": 4357.5,
		"SOS": 1627.699951,
		"SRD": 3.2875,
		"STD": 18823.300781,
		"SVC": 8.7475,
		"SYP": 62.549999,
		"SZL": 7.803,
		"THB": 30.985001,
		"TJS": 4.7587,
		"TMT": 2.852,
		"TND": 1.5479,
		"TOP": 1.700225,
		"TRY": 1.76065,
		"TTD": 6.40375,
		"TWD": 29.336,
		"TZS": 1576.5,
		"UAH": 8.037,
		"UGX": 2485,
		"USD": 1,
		"UYU": 19.870001,
		"UZS": 1856.150024,
		"VEF": 4.295,
		"VND": 20848,
		"VUV": 92.5,
		"WST": 2.265296,
		"XAF": 502.379547,
		"XCD": 2.7,
		"XDR": 0.648021,
		"XOF": 502.899994,
		"XPF": 91.849998,
		"YER": 214.735001,
		"ZAR": 7.80345,
		"ZMK": 5232.5,
		"ZWL": 322.355011
	}
}
