{
	"disclaimer": "This data is collected from various providers and provided free of charge for informational purposes only, with no guarantee whatsoever of accuracy, validity, availability, or fitness for any purpose; use at your own risk. Other than that, have fun! More info: http://openexchangerates.org/terms/",
	"license": "Data collected from various providers with public-facing APIs; copyright may apply; not for resale; no warranties given. Full license info: http://openexchangerates.org/license/",
	"timestamp": 1328744064,
	"base": "USD",
	"rates": {
		"AED": 3.6731,
		"AFN": 44.790001,
		"ALL": 104.660004,
		"AMD": 388.369995,
		"ANG": 1.79,
		"AOA": 95.295502,
		"ARS": 4.337,
		"AUD": 0.927257,
		"AWG": 1.7899,
		"AZN": 0.7863,
		"BAM": 1.48205,
		"BBD": 2,
		"BDT": 84.125,
		"BGN": 1.4784,
		"BHD": 0.37703,
		"BIF": 1305,
		"BMD": 1,
		"BND": 1.24645,
		"BOB": 6.91,
		"BRL": 1.7195,
		"BSD": 1,
		"BTN": 49.154999,
		"BWP": 7.1788,
		"BYR": 8330,
		"BZD": 1.9485,
		"CAD": 0.99625,
		"CDF": 920.026978,
		"CHF": 0.91315,
		"CLF": 0.02129,
		"CLP": 478.019989,
		"CNY": 6.2972,
		"COP": 1779.800049,
		"CRC": 508,
		"CUP": 1,
		"CVE": 83.75,
		"CZK": 18.7295,
		"DJF": 178.5,
		"DKK": 5.6089,
		"DOP": 38.900002,
		"DZD": 74.650002,
		"EGP": 6.0368,
		"ETB": 17.37895,
		"EUR": 0.754461,
		"FJD": 1.7489,
		"FKP": 0.6322,
		"GBP": 0.632311,
		"GEL": 1.67135,
		"GHS": 1.6888,
		"GIP": 0.63215,
		"GMD": 29.709999,
		"GNF": 7212.5,
		"GTQ": 7.7655,
		"GYD": 203.699997,
		"HKD": 7.75395,
		"HNL": 19.055,
		"HRK": 5.7083,
		"HTG": 40.349998,
		"HUF": 220.130005,
		"IDR": 8934,
		"IEP": 0.59393,
		"ILS": 3.71565,
		"INR": 49.150002,
		"IQD": 1165.670044,
		"IRR": 11675,
		"ISK": 122.089996,
		"JMD": 86.300003,
		"JOD": 0.7105,
		"JPY": 77.044998,
		"KES": 82.709999,
		"KGS": 46.860001,
		"KHR": 4047.5,
		"KMF": 371.002441,
		"KPW": 900,
		"KRW": 1117.170044,
		"KWD": 0.27715,
		"KZT": 148.539993,
		"LAK": 8006.299805,
		"LBP": 1504,
		"LKR": 114.260002,
		"LRD": 73.379997,
		"LSL": 7.57,
		"LTL": 2.6052,
		"LVL": 0.5272,
		"LYD": 1.2525,
		"MAD": 8.4224,
		"MDL": 11.955,
		"MGA": 2165,
		"MKD": 46.77,
		"MMK": 6.51,
		"MNT": 1357.5,
		"MOP": 7.986,
		"MRO": 290.380005,
		"MUR": 29.1,
		"MVR": 15.33,
		"MWK": 168.141998,
		"MXN": 12.7245,
		"MYR": 3.003,
		"MZN": 27.066999,
		"NAD": 7.572,
		"NGN": 159.449997,
		"NIO": 23.105,
		"NOK": 5.7588,
		"NPR": 78.389999,
		"NZD": 1.199904,
		"OMR": 0.38505,
		"PAB": 1,
		"PEN": 2.689,
		"PGK": 2.0631,
		"PHP": 42.290001,
		"PKR": 90.610001,
		"PLN": 3.1572,
		"PYG": 4500,
		"QAR": 3.6418,
		"RON": 3.2838,
		"RSD": 81.920502,
		"RUB": 29.744499,
		"RWF": 604.547424,
		"SAR": 3.7502,
		"SBD": 7.050995,
		"SCR": 13.9311,
		"SDG": 2.6783,
		"SEK": 6.6488,
		"SGD": 1.2471,
		"SHP": 0.63215,
		"SLL": 4356.5,
		"SOS": 1627,
		"SRD": 3.2875,
		"STD": 18537.5,
		"SVC": 8.7475,
		"SYP": 57.450001,
		"SZL": 7.57,
		"THB": 30.753,
		"TJS": 4.7583,
		"TMT": 2.8365,
		"TND": 1.4975,
		"TOP": 1.699936,
		"TRY": 1.7489,
		"TTD": 6.39435,
		"TWD": 29.51,
		"TZS": 1593.5,
		"UAH": 8.034,
		"UGX": 2320,
		"USD": 1,
		"UYU": 19.43,
		"UZS": 1816.76001,
		"VEF": 4.2927,
		"VND": 20923,
		"VUV": 90,
		"WST": 2.279758,
		"XAF": 494.669861,
		"XCD": 2.7,
		"XDR": 0.642988,
		"XOF": 494.899994,
		"XPF": 90.129997,
		"YER": 219.255005,
		"ZAR": 7.5705,
		"ZMK": 5207.5,
		"ZWD": 0,
		"ZWL": 322.355011
	}
}
